{
    "Meta Data": {
        "1. Information": "Intraday (60min) prices and volumes",
        "2. Symbol": "FATE",
        "3. Last Refreshed": "2018-01-12 16:00:00",
        "4. Interval": "60min",
        "5. Output Size": "Compact",
        "6. Time Zone": "US/Eastern"
    },
    "Time Series (60min)": {
        "2018-01-12 16:00:00": {
            "1. open": "6.9600",
            "2. high": "7.0300",
            "3. low": "6.9500",
            "4. close": "7.0100",
            "5. volume": "106624"
        },
        "2018-01-12 15:00:00": {
            "1. open": "6.9800",
            "2. high": "7.0100",
            "3. low": "6.9600",
            "4. close": "6.9600",
            "5. volume": "22076"
        },
        "2018-01-12 14:00:00": {
            "1. open": "6.9550",
            "2. high": "7.0100",
            "3. low": "6.8700",
            "4. close": "7.0100",
            "5. volume": "33022"
        },
        "2018-01-12 13:00:00": {
            "1. open": "6.9700",
            "2. high": "6.9800",
            "3. low": "6.8600",
            "4. close": "6.9550",
            "5. volume": "39315"
        },
        "2018-01-12 12:00:00": {
            "1. open": "7.0050",
            "2. high": "7.1000",
            "3. low": "6.8700",
            "4. close": "6.9850",
            "5. volume": "83291"
        },
        "2018-01-12 11:00:00": {
            "1. open": "6.7714",
            "2. high": "7.0000",
            "3. low": "6.7600",
            "4. close": "7.0000",
            "5. volume": "90983"
        },
        "2018-01-12 10:00:00": {
            "1. open": "6.8000",
            "2. high": "6.8600",
            "3. low": "6.7700",
            "4. close": "6.7700",
            "5. volume": "26822"
        },
        "2018-01-11 16:00:00": {
            "1. open": "6.8300",
            "2. high": "6.8800",
            "3. low": "6.7400",
            "4. close": "6.8000",
            "5. volume": "132127"
        },
        "2018-01-11 15:00:00": {
            "1. open": "6.8800",
            "2. high": "6.8800",
            "3. low": "6.7600",
            "4. close": "6.8400",
            "5. volume": "56768"
        },
        "2018-01-11 14:00:00": {
            "1. open": "6.9400",
            "2. high": "6.9400",
            "3. low": "6.8100",
            "4. close": "6.8500",
            "5. volume": "12650"
        },
        "2018-01-11 13:00:00": {
            "1. open": "6.9000",
            "2. high": "6.9500",
            "3. low": "6.8100",
            "4. close": "6.9400",
            "5. volume": "31333"
        },
        "2018-01-11 12:00:00": {
            "1. open": "6.8000",
            "2. high": "6.9200",
            "3. low": "6.7600",
            "4. close": "6.8800",
            "5. volume": "59933"
        },
        "2018-01-11 11:00:00": {
            "1. open": "6.7200",
            "2. high": "6.8000",
            "3. low": "6.6200",
            "4. close": "6.7812",
            "5. volume": "75771"
        },
        "2018-01-11 10:00:00": {
            "1. open": "6.7200",
            "2. high": "6.7500",
            "3. low": "6.6000",
            "4. close": "6.7200",
            "5. volume": "14317"
        },
        "2018-01-10 16:00:00": {
            "1. open": "6.5600",
            "2. high": "6.7100",
            "3. low": "6.5500",
            "4. close": "6.7000",
            "5. volume": "83413"
        },
        "2018-01-10 15:00:00": {
            "1. open": "6.4800",
            "2. high": "6.5500",
            "3. low": "6.4100",
            "4. close": "6.5500",
            "5. volume": "33873"
        },
        "2018-01-10 14:00:00": {
            "1. open": "6.4350",
            "2. high": "6.5300",
            "3. low": "6.4100",
            "4. close": "6.4700",
            "5. volume": "57118"
        },
        "2018-01-10 13:00:00": {
            "1. open": "6.4400",
            "2. high": "6.4500",
            "3. low": "6.4000",
            "4. close": "6.4300",
            "5. volume": "58933"
        },
        "2018-01-10 12:00:00": {
            "1. open": "6.3100",
            "2. high": "6.4600",
            "3. low": "6.3000",
            "4. close": "6.4600",
            "5. volume": "106648"
        },
        "2018-01-10 11:00:00": {
            "1. open": "6.5500",
            "2. high": "6.5500",
            "3. low": "6.2400",
            "4. close": "6.2950",
            "5. volume": "73921"
        },
        "2018-01-10 10:00:00": {
            "1. open": "6.5000",
            "2. high": "6.7000",
            "3. low": "6.4401",
            "4. close": "6.5500",
            "5. volume": "35765"
        },
        "2018-01-09 16:00:00": {
            "1. open": "6.5200",
            "2. high": "6.5600",
            "3. low": "6.5100",
            "4. close": "6.5600",
            "5. volume": "103492"
        },
        "2018-01-09 15:00:00": {
            "1. open": "6.4800",
            "2. high": "6.5750",
            "3. low": "6.4400",
            "4. close": "6.5000",
            "5. volume": "84181"
        },
        "2018-01-09 14:00:00": {
            "1. open": "6.5200",
            "2. high": "6.5600",
            "3. low": "6.4600",
            "4. close": "6.4800",
            "5. volume": "90712"
        },
        "2018-01-09 13:00:00": {
            "1. open": "6.4200",
            "2. high": "6.5500",
            "3. low": "6.3900",
            "4. close": "6.5000",
            "5. volume": "50798"
        },
        "2018-01-09 12:00:00": {
            "1. open": "6.5700",
            "2. high": "6.6100",
            "3. low": "6.4100",
            "4. close": "6.4200",
            "5. volume": "102944"
        },
        "2018-01-09 11:00:00": {
            "1. open": "6.6600",
            "2. high": "6.6990",
            "3. low": "6.5600",
            "4. close": "6.5700",
            "5. volume": "58434"
        },
        "2018-01-09 10:00:00": {
            "1. open": "6.6300",
            "2. high": "6.6650",
            "3. low": "6.5300",
            "4. close": "6.6500",
            "5. volume": "40422"
        },
        "2018-01-08 16:00:00": {
            "1. open": "6.4390",
            "2. high": "6.6000",
            "3. low": "6.4295",
            "4. close": "6.5900",
            "5. volume": "116639"
        },
        "2018-01-08 15:00:00": {
            "1. open": "6.4100",
            "2. high": "6.4800",
            "3. low": "6.3500",
            "4. close": "6.4250",
            "5. volume": "55128"
        },
        "2018-01-08 14:00:00": {
            "1. open": "6.3900",
            "2. high": "6.5000",
            "3. low": "6.2900",
            "4. close": "6.4000",
            "5. volume": "130246"
        },
        "2018-01-08 13:00:00": {
            "1. open": "6.4400",
            "2. high": "6.4550",
            "3. low": "6.2600",
            "4. close": "6.3900",
            "5. volume": "89081"
        },
        "2018-01-08 12:00:00": {
            "1. open": "6.6000",
            "2. high": "6.6200",
            "3. low": "6.3600",
            "4. close": "6.4400",
            "5. volume": "101187"
        },
        "2018-01-08 11:00:00": {
            "1. open": "6.6950",
            "2. high": "6.7400",
            "3. low": "6.5200",
            "4. close": "6.6000",
            "5. volume": "84188"
        },
        "2018-01-08 10:00:00": {
            "1. open": "6.8500",
            "2. high": "6.9300",
            "3. low": "6.6600",
            "4. close": "6.6900",
            "5. volume": "79768"
        },
        "2018-01-05 16:00:00": {
            "1. open": "6.7200",
            "2. high": "6.8200",
            "3. low": "6.6899",
            "4. close": "6.8200",
            "5. volume": "129426"
        },
        "2018-01-05 15:00:00": {
            "1. open": "6.7200",
            "2. high": "6.7500",
            "3. low": "6.6800",
            "4. close": "6.7200",
            "5. volume": "72507"
        },
        "2018-01-05 14:00:00": {
            "1. open": "6.7700",
            "2. high": "6.8000",
            "3. low": "6.6510",
            "4. close": "6.7300",
            "5. volume": "65625"
        },
        "2018-01-05 13:00:00": {
            "1. open": "6.9800",
            "2. high": "6.9899",
            "3. low": "6.7700",
            "4. close": "6.7800",
            "5. volume": "71381"
        },
        "2018-01-05 12:00:00": {
            "1. open": "7.1275",
            "2. high": "7.1275",
            "3. low": "6.8200",
            "4. close": "6.9754",
            "5. volume": "115626"
        },
        "2018-01-05 11:00:00": {
            "1. open": "7.0900",
            "2. high": "7.2500",
            "3. low": "7.0800",
            "4. close": "7.1400",
            "5. volume": "70896"
        },
        "2018-01-05 10:00:00": {
            "1. open": "7.1500",
            "2. high": "7.2500",
            "3. low": "7.0500",
            "4. close": "7.1000",
            "5. volume": "135644"
        },
        "2018-01-04 16:00:00": {
            "1. open": "7.0932",
            "2. high": "7.1400",
            "3. low": "6.9500",
            "4. close": "6.9900",
            "5. volume": "127081"
        },
        "2018-01-04 15:00:00": {
            "1. open": "7.0500",
            "2. high": "7.2000",
            "3. low": "7.0200",
            "4. close": "7.0910",
            "5. volume": "87401"
        },
        "2018-01-04 14:00:00": {
            "1. open": "6.6900",
            "2. high": "7.1600",
            "3. low": "6.6900",
            "4. close": "7.0200",
            "5. volume": "225015"
        },
        "2018-01-04 13:00:00": {
            "1. open": "6.6100",
            "2. high": "6.6916",
            "3. low": "6.5900",
            "4. close": "6.6916",
            "5. volume": "36993"
        },
        "2018-01-04 12:00:00": {
            "1. open": "6.6100",
            "2. high": "6.6299",
            "3. low": "6.5300",
            "4. close": "6.6000",
            "5. volume": "59011"
        },
        "2018-01-04 11:00:00": {
            "1. open": "6.5900",
            "2. high": "6.6300",
            "3. low": "6.5200",
            "4. close": "6.6100",
            "5. volume": "49592"
        },
        "2018-01-04 10:00:00": {
            "1. open": "6.5500",
            "2. high": "6.6350",
            "3. low": "6.5014",
            "4. close": "6.5800",
            "5. volume": "71608"
        },
        "2018-01-03 16:00:00": {
            "1. open": "6.4500",
            "2. high": "6.5500",
            "3. low": "6.4500",
            "4. close": "6.5000",
            "5. volume": "80980"
        },
        "2018-01-03 15:00:00": {
            "1. open": "6.4700",
            "2. high": "6.5500",
            "3. low": "6.4200",
            "4. close": "6.4600",
            "5. volume": "68353"
        },
        "2018-01-03 14:00:00": {
            "1. open": "6.3500",
            "2. high": "6.4900",
            "3. low": "6.3400",
            "4. close": "6.4650",
            "5. volume": "25177"
        },
        "2018-01-03 13:00:00": {
            "1. open": "6.4700",
            "2. high": "6.4800",
            "3. low": "6.3100",
            "4. close": "6.3450",
            "5. volume": "46136"
        },
        "2018-01-03 12:00:00": {
            "1. open": "6.4100",
            "2. high": "6.5000",
            "3. low": "6.3950",
            "4. close": "6.4100",
            "5. volume": "41624"
        },
        "2018-01-03 11:00:00": {
            "1. open": "6.4000",
            "2. high": "6.5500",
            "3. low": "6.3850",
            "4. close": "6.4100",
            "5. volume": "91936"
        },
        "2018-01-03 10:00:00": {
            "1. open": "6.3600",
            "2. high": "6.4900",
            "3. low": "6.3000",
            "4. close": "6.3900",
            "5. volume": "87361"
        },
        "2018-01-02 16:00:00": {
            "1. open": "6.2500",
            "2. high": "6.3100",
            "3. low": "6.2200",
            "4. close": "6.3000",
            "5. volume": "133899"
        },
        "2018-01-02 15:00:00": {
            "1. open": "6.2100",
            "2. high": "6.3100",
            "3. low": "6.2100",
            "4. close": "6.2500",
            "5. volume": "74177"
        },
        "2018-01-02 14:00:00": {
            "1. open": "6.1720",
            "2. high": "6.2400",
            "3. low": "6.1300",
            "4. close": "6.2400",
            "5. volume": "26947"
        },
        "2018-01-02 13:00:00": {
            "1. open": "6.2400",
            "2. high": "6.2900",
            "3. low": "6.1200",
            "4. close": "6.1599",
            "5. volume": "46524"
        },
        "2018-01-02 12:00:00": {
            "1. open": "6.2400",
            "2. high": "6.2500",
            "3. low": "6.1500",
            "4. close": "6.2400",
            "5. volume": "103784"
        },
        "2018-01-02 11:00:00": {
            "1. open": "6.3000",
            "2. high": "6.3700",
            "3. low": "6.1900",
            "4. close": "6.2500",
            "5. volume": "123082"
        },
        "2018-01-02 10:00:00": {
            "1. open": "6.1000",
            "2. high": "6.3198",
            "3. low": "5.9015",
            "4. close": "6.3000",
            "5. volume": "67425"
        },
        "2017-12-29 16:00:00": {
            "1. open": "6.1400",
            "2. high": "6.1450",
            "3. low": "6.1000",
            "4. close": "6.1100",
            "5. volume": "67367"
        },
        "2017-12-29 15:00:00": {
            "1. open": "6.2000",
            "2. high": "6.2100",
            "3. low": "6.1300",
            "4. close": "6.1450",
            "5. volume": "38108"
        },
        "2017-12-29 14:00:00": {
            "1. open": "6.2900",
            "2. high": "6.3300",
            "3. low": "6.1900",
            "4. close": "6.2200",
            "5. volume": "32311"
        },
        "2017-12-29 13:00:00": {
            "1. open": "6.2200",
            "2. high": "6.3400",
            "3. low": "6.2200",
            "4. close": "6.2900",
            "5. volume": "74595"
        },
        "2017-12-29 12:00:00": {
            "1. open": "6.1600",
            "2. high": "6.2600",
            "3. low": "6.1002",
            "4. close": "6.2100",
            "5. volume": "89134"
        },
        "2017-12-29 11:00:00": {
            "1. open": "6.0700",
            "2. high": "6.3200",
            "3. low": "6.0550",
            "4. close": "6.1500",
            "5. volume": "211873"
        },
        "2017-12-29 10:00:00": {
            "1. open": "6.0800",
            "2. high": "6.1200",
            "3. low": "6.0100",
            "4. close": "6.0750",
            "5. volume": "36662"
        }
    }
}