{
    "Meta Data": {
        "1. Information": "Intraday (60min) prices and volumes",
        "2. Symbol": "CLDR",
        "3. Last Refreshed": "2018-01-12 16:00:00",
        "4. Interval": "60min",
        "5. Output Size": "Compact",
        "6. Time Zone": "US/Eastern"
    },
    "Time Series (60min)": {
        "2018-01-12 16:00:00": {
            "1. open": "18.1100",
            "2. high": "18.1900",
            "3. low": "18.0400",
            "4. close": "18.1400",
            "5. volume": "400969"
        },
        "2018-01-12 15:00:00": {
            "1. open": "18.4200",
            "2. high": "18.4200",
            "3. low": "18.0750",
            "4. close": "18.1100",
            "5. volume": "332513"
        },
        "2018-01-12 14:00:00": {
            "1. open": "18.5800",
            "2. high": "18.6000",
            "3. low": "18.2549",
            "4. close": "18.4200",
            "5. volume": "395079"
        },
        "2018-01-12 13:00:00": {
            "1. open": "18.5500",
            "2. high": "18.6800",
            "3. low": "18.5000",
            "4. close": "18.5700",
            "5. volume": "172059"
        },
        "2018-01-12 12:00:00": {
            "1. open": "18.1600",
            "2. high": "18.6100",
            "3. low": "18.1450",
            "4. close": "18.5500",
            "5. volume": "332771"
        },
        "2018-01-12 11:00:00": {
            "1. open": "18.2200",
            "2. high": "18.3400",
            "3. low": "18.0700",
            "4. close": "18.1400",
            "5. volume": "169550"
        },
        "2018-01-12 10:00:00": {
            "1. open": "18.1000",
            "2. high": "18.4800",
            "3. low": "18.0000",
            "4. close": "18.2250",
            "5. volume": "247230"
        },
        "2018-01-11 16:00:00": {
            "1. open": "17.8945",
            "2. high": "17.9000",
            "3. low": "17.8600",
            "4. close": "17.9000",
            "5. volume": "278650"
        },
        "2018-01-11 15:00:00": {
            "1. open": "17.9300",
            "2. high": "18.0200",
            "3. low": "17.8800",
            "4. close": "17.8900",
            "5. volume": "179806"
        },
        "2018-01-11 14:00:00": {
            "1. open": "18.0950",
            "2. high": "18.1139",
            "3. low": "17.9200",
            "4. close": "17.9200",
            "5. volume": "187619"
        },
        "2018-01-11 13:00:00": {
            "1. open": "18.1150",
            "2. high": "18.1500",
            "3. low": "18.0250",
            "4. close": "18.0953",
            "5. volume": "142079"
        },
        "2018-01-11 12:00:00": {
            "1. open": "18.1450",
            "2. high": "18.1600",
            "3. low": "18.0600",
            "4. close": "18.1150",
            "5. volume": "198201"
        },
        "2018-01-11 11:00:00": {
            "1. open": "18.3800",
            "2. high": "18.4317",
            "3. low": "18.0500",
            "4. close": "18.1500",
            "5. volume": "229533"
        },
        "2018-01-11 10:00:00": {
            "1. open": "18.3800",
            "2. high": "18.4375",
            "3. low": "18.1200",
            "4. close": "18.3700",
            "5. volume": "188589"
        },
        "2018-01-10 16:00:00": {
            "1. open": "18.4150",
            "2. high": "18.4400",
            "3. low": "18.1800",
            "4. close": "18.2688",
            "5. volume": "590308"
        },
        "2018-01-10 15:00:00": {
            "1. open": "18.3500",
            "2. high": "18.4800",
            "3. low": "18.2300",
            "4. close": "18.4000",
            "5. volume": "252085"
        },
        "2018-01-10 14:00:00": {
            "1. open": "18.1300",
            "2. high": "18.3700",
            "3. low": "18.0500",
            "4. close": "18.3400",
            "5. volume": "220303"
        },
        "2018-01-10 13:00:00": {
            "1. open": "18.2900",
            "2. high": "18.3500",
            "3. low": "18.1100",
            "4. close": "18.1100",
            "5. volume": "271947"
        },
        "2018-01-10 12:00:00": {
            "1. open": "18.2700",
            "2. high": "18.4300",
            "3. low": "18.1700",
            "4. close": "18.3100",
            "5. volume": "560939"
        },
        "2018-01-10 11:00:00": {
            "1. open": "18.1900",
            "2. high": "18.3200",
            "3. low": "17.9000",
            "4. close": "18.2700",
            "5. volume": "772338"
        },
        "2018-01-10 10:00:00": {
            "1. open": "17.7400",
            "2. high": "18.2001",
            "3. low": "17.5200",
            "4. close": "18.1800",
            "5. volume": "968317"
        },
        "2018-01-09 16:00:00": {
            "1. open": "17.2450",
            "2. high": "17.2500",
            "3. low": "17.1800",
            "4. close": "17.1800",
            "5. volume": "171406"
        },
        "2018-01-09 15:00:00": {
            "1. open": "17.2000",
            "2. high": "17.2500",
            "3. low": "17.1500",
            "4. close": "17.2400",
            "5. volume": "96940"
        },
        "2018-01-09 14:00:00": {
            "1. open": "17.1200",
            "2. high": "17.2300",
            "3. low": "17.1100",
            "4. close": "17.2000",
            "5. volume": "116962"
        },
        "2018-01-09 13:00:00": {
            "1. open": "17.0000",
            "2. high": "17.1200",
            "3. low": "16.9900",
            "4. close": "17.1100",
            "5. volume": "70005"
        },
        "2018-01-09 12:00:00": {
            "1. open": "17.0200",
            "2. high": "17.0400",
            "3. low": "16.9400",
            "4. close": "17.0100",
            "5. volume": "72127"
        },
        "2018-01-09 11:00:00": {
            "1. open": "17.0800",
            "2. high": "17.0800",
            "3. low": "16.9500",
            "4. close": "17.0400",
            "5. volume": "159289"
        },
        "2018-01-09 10:00:00": {
            "1. open": "17.1200",
            "2. high": "17.2800",
            "3. low": "17.0700",
            "4. close": "17.0700",
            "5. volume": "73085"
        },
        "2018-01-08 16:00:00": {
            "1. open": "17.0800",
            "2. high": "17.2100",
            "3. low": "17.0800",
            "4. close": "17.1600",
            "5. volume": "170608"
        },
        "2018-01-08 15:00:00": {
            "1. open": "16.9400",
            "2. high": "17.1400",
            "3. low": "16.9350",
            "4. close": "17.0800",
            "5. volume": "159118"
        },
        "2018-01-08 14:00:00": {
            "1. open": "16.8600",
            "2. high": "16.9800",
            "3. low": "16.8600",
            "4. close": "16.9400",
            "5. volume": "32470"
        },
        "2018-01-08 13:00:00": {
            "1. open": "16.9858",
            "2. high": "17.0100",
            "3. low": "16.8500",
            "4. close": "16.8600",
            "5. volume": "65922"
        },
        "2018-01-08 12:00:00": {
            "1. open": "16.9100",
            "2. high": "16.9900",
            "3. low": "16.8900",
            "4. close": "16.9850",
            "5. volume": "59961"
        },
        "2018-01-08 11:00:00": {
            "1. open": "16.8500",
            "2. high": "17.0000",
            "3. low": "16.7030",
            "4. close": "16.9323",
            "5. volume": "143067"
        },
        "2018-01-08 10:00:00": {
            "1. open": "17.2000",
            "2. high": "17.2000",
            "3. low": "16.8500",
            "4. close": "16.8500",
            "5. volume": "124315"
        },
        "2018-01-05 16:00:00": {
            "1. open": "17.3300",
            "2. high": "17.3300",
            "3. low": "17.2200",
            "4. close": "17.2500",
            "5. volume": "182384"
        },
        "2018-01-05 15:00:00": {
            "1. open": "17.3100",
            "2. high": "17.3500",
            "3. low": "17.2800",
            "4. close": "17.3200",
            "5. volume": "63588"
        },
        "2018-01-05 14:00:00": {
            "1. open": "17.2800",
            "2. high": "17.3500",
            "3. low": "17.2501",
            "4. close": "17.3150",
            "5. volume": "46094"
        },
        "2018-01-05 13:00:00": {
            "1. open": "17.4000",
            "2. high": "17.4000",
            "3. low": "17.2600",
            "4. close": "17.2900",
            "5. volume": "46252"
        },
        "2018-01-05 12:00:00": {
            "1. open": "17.2650",
            "2. high": "17.4100",
            "3. low": "17.2300",
            "4. close": "17.4000",
            "5. volume": "103964"
        },
        "2018-01-05 11:00:00": {
            "1. open": "17.2900",
            "2. high": "17.2900",
            "3. low": "17.1800",
            "4. close": "17.2650",
            "5. volume": "68019"
        },
        "2018-01-05 10:00:00": {
            "1. open": "17.2500",
            "2. high": "17.3500",
            "3. low": "17.2000",
            "4. close": "17.2400",
            "5. volume": "33435"
        },
        "2018-01-04 16:00:00": {
            "1. open": "17.2950",
            "2. high": "17.3100",
            "3. low": "17.2400",
            "4. close": "17.2500",
            "5. volume": "191616"
        },
        "2018-01-04 15:00:00": {
            "1. open": "17.3331",
            "2. high": "17.3900",
            "3. low": "17.2300",
            "4. close": "17.3000",
            "5. volume": "93254"
        },
        "2018-01-04 14:00:00": {
            "1. open": "17.2600",
            "2. high": "17.3600",
            "3. low": "17.2400",
            "4. close": "17.3300",
            "5. volume": "50150"
        },
        "2018-01-04 13:00:00": {
            "1. open": "17.3200",
            "2. high": "17.3600",
            "3. low": "17.2475",
            "4. close": "17.2600",
            "5. volume": "68519"
        },
        "2018-01-04 12:00:00": {
            "1. open": "17.2375",
            "2. high": "17.3400",
            "3. low": "17.1600",
            "4. close": "17.3200",
            "5. volume": "75292"
        },
        "2018-01-04 11:00:00": {
            "1. open": "17.3950",
            "2. high": "17.4000",
            "3. low": "17.1600",
            "4. close": "17.2400",
            "5. volume": "173655"
        },
        "2018-01-04 10:00:00": {
            "1. open": "17.5100",
            "2. high": "17.7000",
            "3. low": "17.3700",
            "4. close": "17.4000",
            "5. volume": "102869"
        },
        "2018-01-03 16:00:00": {
            "1. open": "17.5800",
            "2. high": "17.6000",
            "3. low": "17.4900",
            "4. close": "17.5250",
            "5. volume": "194080"
        },
        "2018-01-03 15:00:00": {
            "1. open": "17.5000",
            "2. high": "17.5850",
            "3. low": "17.5000",
            "4. close": "17.5750",
            "5. volume": "62728"
        },
        "2018-01-03 14:00:00": {
            "1. open": "17.5200",
            "2. high": "17.5900",
            "3. low": "17.4600",
            "4. close": "17.5100",
            "5. volume": "96737"
        },
        "2018-01-03 13:00:00": {
            "1. open": "17.5000",
            "2. high": "17.5800",
            "3. low": "17.4700",
            "4. close": "17.5150",
            "5. volume": "73348"
        },
        "2018-01-03 12:00:00": {
            "1. open": "17.5800",
            "2. high": "17.6200",
            "3. low": "17.4700",
            "4. close": "17.4900",
            "5. volume": "110300"
        },
        "2018-01-03 11:00:00": {
            "1. open": "17.5600",
            "2. high": "17.6000",
            "3. low": "17.4400",
            "4. close": "17.5750",
            "5. volume": "135955"
        },
        "2018-01-03 10:00:00": {
            "1. open": "17.3000",
            "2. high": "17.5700",
            "3. low": "17.3000",
            "4. close": "17.5300",
            "5. volume": "94184"
        },
        "2018-01-02 16:00:00": {
            "1. open": "17.2750",
            "2. high": "17.4100",
            "3. low": "17.2600",
            "4. close": "17.3800",
            "5. volume": "432889"
        },
        "2018-01-02 15:00:00": {
            "1. open": "17.2700",
            "2. high": "17.3600",
            "3. low": "17.2300",
            "4. close": "17.2700",
            "5. volume": "256136"
        },
        "2018-01-02 14:00:00": {
            "1. open": "17.1200",
            "2. high": "17.2700",
            "3. low": "17.1150",
            "4. close": "17.2700",
            "5. volume": "179831"
        },
        "2018-01-02 13:00:00": {
            "1. open": "16.9900",
            "2. high": "17.1800",
            "3. low": "16.9900",
            "4. close": "17.1150",
            "5. volume": "237461"
        },
        "2018-01-02 12:00:00": {
            "1. open": "16.8200",
            "2. high": "17.0200",
            "3. low": "16.7200",
            "4. close": "16.9800",
            "5. volume": "169184"
        },
        "2018-01-02 11:00:00": {
            "1. open": "16.8100",
            "2. high": "16.8400",
            "3. low": "16.6900",
            "4. close": "16.8300",
            "5. volume": "67340"
        },
        "2018-01-02 10:00:00": {
            "1. open": "16.4200",
            "2. high": "16.7700",
            "3. low": "16.3573",
            "4. close": "16.7655",
            "5. volume": "65677"
        },
        "2017-12-29 16:00:00": {
            "1. open": "16.4201",
            "2. high": "16.5850",
            "3. low": "16.4200",
            "4. close": "16.5200",
            "5. volume": "337282"
        },
        "2017-12-29 15:00:00": {
            "1. open": "16.4100",
            "2. high": "16.4500",
            "3. low": "16.3500",
            "4. close": "16.4200",
            "5. volume": "158574"
        },
        "2017-12-29 14:00:00": {
            "1. open": "16.5178",
            "2. high": "16.5500",
            "3. low": "16.3800",
            "4. close": "16.4100",
            "5. volume": "90150"
        },
        "2017-12-29 13:00:00": {
            "1. open": "16.6700",
            "2. high": "16.6800",
            "3. low": "16.5100",
            "4. close": "16.5200",
            "5. volume": "42817"
        },
        "2017-12-29 12:00:00": {
            "1. open": "16.5800",
            "2. high": "16.6800",
            "3. low": "16.5300",
            "4. close": "16.6400",
            "5. volume": "88607"
        },
        "2017-12-29 11:00:00": {
            "1. open": "16.6800",
            "2. high": "16.6800",
            "3. low": "16.5300",
            "4. close": "16.5700",
            "5. volume": "61226"
        },
        "2017-12-29 10:00:00": {
            "1. open": "16.6400",
            "2. high": "16.7200",
            "3. low": "16.5700",
            "4. close": "16.6600",
            "5. volume": "53203"
        }
    }
}